cortex4py/api.py
cortex4py/exceptions.py
cortex4py/query.py
cortex4py/controllers/__init__.py
cortex4py/controllers/abstract.py
cortex4py/controllers/analyzers.py
cortex4py/controllers/jobs.py
cortex4py/controllers/organizations.py
cortex4py/controllers/responders.py
cortex4py/controllers/users.py
cortex4py/models/__init__.py
cortex4py/models/analyzer.py
cortex4py/models/analyzer_definition.py
cortex4py/models/job.py
cortex4py/models/job_artifact.py
cortex4py/models/model.py
cortex4py/models/organization.py
cortex4py/models/responder.py
cortex4py/models/responder_definition.py
cortex4py/models/user.py
cortex4py-2.1.0.dist-info/AUTHORS
cortex4py-2.1.0.dist-info/LICENSE
cortex4py-2.1.0.dist-info/METADATA
cortex4py-2.1.0.dist-info/WHEEL
cortex4py-2.1.0.dist-info/top_level.txt
cortex4py-2.1.0.dist-info/RECORD
