Metadata-Version: 2.1
Name: cortex4py
Version: 2.1.0
Summary: Python API client for Cortex.
Home-page: https://github.com/Thehive-Project/Cortex4py
Author: TheHive-Project
Author-email: support@thehive-project.org
Maintainer: TheHive-Project
License: AGPL-V3
Platform: UNKNOWN
Classifier: Development Status :: 4 - Beta
Classifier: Intended Audience :: Developers
Classifier: Intended Audience :: Information Technology
Classifier: Intended Audience :: Science/Research
Classifier: License :: OSI Approved :: GNU Affero General Public License v3 or later (AGPLv3+)
Classifier: Natural Language :: English
Classifier: Operating System :: OS Independent
Classifier: Programming Language :: Python
Classifier: Topic :: Security
Classifier: Topic :: Software Development :: Libraries :: Python Modules
Requires-Dist: typing
Requires-Dist: requests
Requires-Dist: python-magic
